// class version 61.0 (61)
// access flags 0x21
public class DebtCollect/DebtPaybackTest {

  // compiled from: DebtPaybackTest.java

  // access flags 0x1
  public <init>()V
   L0
    LINENUMBER 7 L0
    ALOAD 0
    INVOKESPECIAL java/lang/Object.<init> ()V
    RETURN
   L1
    LOCALVARIABLE this LDebtCollect/DebtPaybackTest; L0 L1 0
    MAXSTACK = 1
    MAXLOCALS = 1

  // access flags 0x1
  public testMonthly_rate()V
  @Lorg/junit/jupiter/api/Test;()
   L0
    LINENUMBER 12 L0
    DCONST_0
    NEW DebtCollect/DebtPayback
    INVOKESPECIAL DebtCollect/DebtPayback.<init> ()V
    DCONST_0
    DCONST_0
    INVOKESTATIC DebtCollect/DebtPayback.monthly_rate (DD)D
    INVOKESTATIC org/junit/jupiter/api/Assertions.assertEquals (DD)V
   L1
    LINENUMBER 13 L1
    DCONST_0
    NEW DebtCollect/DebtPayback
    INVOKESPECIAL DebtCollect/DebtPayback.<init> ()V
    LDC -2.0
    LDC -100.0
    INVOKESTATIC DebtCollect/DebtPayback.monthly_rate (DD)D
    POP2
    POP2
   L2
    LINENUMBER 14 L2
    LDC 50.0
    NEW DebtCollect/DebtPayback
    INVOKESPECIAL DebtCollect/DebtPayback.<init> ()V
    LDC 5000.0
    LDC 12.0
    INVOKESTATIC DebtCollect/DebtPayback.monthly_rate (DD)D
    INVOKESTATIC org/junit/jupiter/api/Assertions.assertEquals (DD)V
   L3
    LINENUMBER 15 L3
    LDC 60.0
    NEW DebtCollect/DebtPayback
    INVOKESPECIAL DebtCollect/DebtPayback.<init> ()V
    LDC 6000.0
    LDC 12.0
    INVOKESTATIC DebtCollect/DebtPayback.monthly_rate (DD)D
    INVOKESTATIC org/junit/jupiter/api/Assertions.assertEquals (DD)V
   L4
    LINENUMBER 16 L4
    RETURN
   L5
    LOCALVARIABLE this LDebtCollect/DebtPaybackTest; L0 L5 0
    MAXSTACK = 6
    MAXLOCALS = 1

  // access flags 0x1
  public testNumber_rate()V
  @Lorg/junit/jupiter/api/Test;()
   L0
    LINENUMBER 21 L0
    DCONST_0
    NEW DebtCollect/DebtPayback
    INVOKESPECIAL DebtCollect/DebtPayback.<init> ()V
    DCONST_0
    INVOKESTATIC DebtCollect/DebtPayback.number_rate (D)D
    INVOKESTATIC org/junit/jupiter/api/Assertions.assertEquals (DD)V
   L1
    LINENUMBER 22 L1
    DCONST_0
    NEW DebtCollect/DebtPayback
    INVOKESPECIAL DebtCollect/DebtPayback.<init> ()V
    LDC -1.0
    INVOKESTATIC DebtCollect/DebtPayback.number_rate (D)D
    INVOKESTATIC org/junit/jupiter/api/Assertions.assertEquals (DD)V
   L2
    LINENUMBER 23 L2
    DCONST_1
    NEW DebtCollect/DebtPayback
    INVOKESPECIAL DebtCollect/DebtPayback.<init> ()V
    LDC 12.0
    INVOKESTATIC DebtCollect/DebtPayback.number_rate (D)D
    INVOKESTATIC org/junit/jupiter/api/Assertions.assertEquals (DD)V
   L3
    LINENUMBER 24 L3
    RETURN
   L4
    LOCALVARIABLE this LDebtCollect/DebtPaybackTest; L0 L4 0
    MAXSTACK = 4
    MAXLOCALS = 1

  // access flags 0x1
  public testAmount_()V
  @Lorg/junit/jupiter/api/Test;()
   L0
    LINENUMBER 29 L0
    DCONST_0
    NEW DebtCollect/DebtPayback
    INVOKESPECIAL DebtCollect/DebtPayback.<init> ()V
    LDC -1.0
    LDC -1.0
    ICONST_M1
    INVOKESTATIC DebtCollect/DebtPayback.amount_ (DDI)D
    INVOKESTATIC org/junit/jupiter/api/Assertions.assertEquals (DD)V
   L1
    LINENUMBER 30 L1
    DCONST_0
    NEW DebtCollect/DebtPayback
    INVOKESPECIAL DebtCollect/DebtPayback.<init> ()V
    DCONST_0
    DCONST_0
    ICONST_0
    INVOKESTATIC DebtCollect/DebtPayback.amount_ (DDI)D
    INVOKESTATIC org/junit/jupiter/api/Assertions.assertEquals (DD)V
   L2
    LINENUMBER 31 L2
    LDC 5300.0
    NEW DebtCollect/DebtPayback
    INVOKESPECIAL DebtCollect/DebtPayback.<init> ()V
    LDC 5000.0
    LDC 12.0
    BIPUSH 6
    INVOKESTATIC DebtCollect/DebtPayback.amount_ (DDI)D
    INVOKESTATIC org/junit/jupiter/api/Assertions.assertEquals (DD)V
   L3
    LINENUMBER 32 L3
    RETURN
   L4
    LOCALVARIABLE this LDebtCollect/DebtPaybackTest; L0 L4 0
    MAXSTACK = 7
    MAXLOCALS = 1
}

V
   L3
    LINENUMBER 31 L3
    RETURN
   L4
    LOCALVARIABLE this LDebtCollect/DebtPaybackTest; L0 L4 0
    MAXSTACK = 7
    MAXLOCALS = 1
}

