// class version 61.0 (61)
// access flags 0x20
class DebtCollect/DebtPayback$LoanParameters {

  // compiled from: DebtPayback.java
  NESTHOST DebtCollect/DebtPayback
  // access flags 0xA
  private static INNERCLASS DebtCollect/DebtPayback$LoanParameters DebtCollect/DebtPayback LoanParameters

  // access flags 0x12
  private final D monthlyPayment

  // access flags 0x12
  private final I numberOfPayments

  // access flags 0x12
  private final D overallDebt

  // access flags 0x1
  public <init>(DID)V
   L0
    LINENUMBER 47 L0
    ALOAD 0
    INVOKESPECIAL java/lang/Object.<init> ()V
   L1
    LINENUMBER 48 L1
    ALOAD 0
    DLOAD 1
    PUTFIELD DebtCollect/DebtPayback$LoanParameters.monthlyPayment : D
   L2
    LINENUMBER 49 L2
    ALOAD 0
    ILOAD 3
    PUTFIELD DebtCollect/DebtPayback$LoanParameters.numberOfPayments : I
   L3
    LINENUMBER 50 L3
    ALOAD 0
    DLOAD 4
    PUTFIELD DebtCollect/DebtPayback$LoanParameters.overallDebt : D
   L4
    LINENUMBER 51 L4
    RETURN
    MAXSTACK = 3
    MAXLOCALS = 6

  // access flags 0x1
  public getMonthlyPayment()D
   L0
    LINENUMBER 54 L0
    ALOAD 0
    GETFIELD DebtCollect/DebtPayback$LoanParameters.monthlyPayment : D
    POP2
    DCONST_0
    DRETURN
    MAXSTACK = 2
    MAXLOCALS = 1

  // access flags 0x1
  public getNumberOfPayments()I
   L0
    LINENUMBER 58 L0
    ALOAD 0
    GETFIELD DebtCollect/DebtPayback$LoanParameters.numberOfPayments : I
    IRETURN
    MAXSTACK = 1
    MAXLOCALS = 1

  // access flags 0x1
  public getOverallDebt()D
   L0
    LINENUMBER 62 L0
    ALOAD 0
    GETFIELD DebtCollect/DebtPayback$LoanParameters.overallDebt : D
    DRETURN
    MAXSTACK = 2
    MAXLOCALS = 1
}

ameters.numberOfPayments : I
    IRETURN
   L1
    LOCALVARIABLE this LDebtCollect/DebtPayback$LoanParameters; L0 L1 0
    MAXSTACK = 1
    MAXLOCALS = 1

  // access flags 0x1
  public getOverallDebt()D
   L0
    LINENUMBER 62 L0
    ALOAD 0
    GETFIELD DebtCollect/DebtPayback$LoanParameters.overallDebt : D
    DRETURN
   L1
    LOCALVARIABLE this LDebtCollect/DebtPayback$LoanParameters; L0 L1 0
    MAXSTACK = 2
    MAXLOCALS = 1
}

