// class version 61.0 (61)
// access flags 0x21
public class DebtCollect/DebtPaybackCal {

  // compiled from: DebtPaybackCal.java
  // access flags 0x19
  public final static INNERCLASS java/lang/invoke/MethodHandles$Lookup java/lang/invoke/MethodHandles Lookup

  // access flags 0x1
  public <init>()V
   L0
    LINENUMBER 4 L0
    ALOAD 0
    INVOKESPECIAL java/lang/Object.<init> ()V
    RETURN
   L1
    LOCALVARIABLE this LDebtCollect/DebtPaybackCal; L0 L1 0
    MAXSTACK = 1
    MAXLOCALS = 1

  // access flags 0x9
  public static main([Ljava/lang/String;)V
   L0
    LINENUMBER 10 L0
    NEW java/util/Scanner
    DUP
    GETSTATIC java/lang/System.in : Ljava/io/InputStream;
    INVOKESPECIAL java/util/Scanner.<init> (Ljava/io/InputStream;)V
    ASTORE 1
   L1
    LINENUMBER 11 L1
    GETSTATIC java/lang/System.out : Ljava/io/PrintStream;
    LDC "Enter Debt Value"
    INVOKEVIRTUAL java/io/PrintStream.println (Ljava/lang/String;)V
   L2
    LINENUMBER 12 L2
    ALOAD 1
    INVOKEVIRTUAL java/util/Scanner.nextDouble ()D
    DSTORE 2
   L3
    LINENUMBER 13 L3
    GETSTATIC java/lang/System.out : Ljava/io/PrintStream;
    LDC "Enter Interest Rate"
    INVOKEVIRTUAL java/io/PrintStream.println (Ljava/lang/String;)V
   L4
    LINENUMBER 14 L4
    ALOAD 1
    INVOKEVIRTUAL java/util/Scanner.nextDouble ()D
    DSTORE 4
   L5
    LINENUMBER 15 L5
    GETSTATIC java/lang/System.out : Ljava/io/PrintStream;
    LDC "Enter Duration in months"
    INVOKEVIRTUAL java/io/PrintStream.println (Ljava/lang/String;)V
   L6
    LINENUMBER 16 L6
    ALOAD 1
    INVOKEVIRTUAL java/util/Scanner.nextInt ()I
    ISTORE 6
   L7
    LINENUMBER 17 L7
    GETSTATIC java/lang/System.out : Ljava/io/PrintStream;
    DLOAD 2
    INVOKEDYNAMIC makeConcatWithConstants(D)Ljava/lang/String; [
      // handle kind 0x6 : INVOKESTATIC
      java/lang/invoke/StringConcatFactory.makeConcatWithConstants(Ljava/lang/invoke/MethodHandles$Lookup;Ljava/lang/String;Ljava/lang/invoke/MethodType;Ljava/lang/String;[Ljava/lang/Object;)Ljava/lang/invoke/CallSite;
      // arguments:
      "Debt: \u0001"
    ]
    INVOKEVIRTUAL java/io/PrintStream.println (Ljava/lang/String;)V
   L8
    LINENUMBER 18 L8
    GETSTATIC java/lang/System.out : Ljava/io/PrintStream;
    DLOAD 4
    INVOKEDYNAMIC makeConcatWithConstants(D)Ljava/lang/String; [
      // handle kind 0x6 : INVOKESTATIC
      java/lang/invoke/StringConcatFactory.makeConcatWithConstants(Ljava/lang/invoke/MethodHandles$Lookup;Ljava/lang/String;Ljava/lang/invoke/MethodType;Ljava/lang/String;[Ljava/lang/Object;)Ljava/lang/invoke/CallSite;
      // arguments:
      "Interest rate: \u0001"
    ]
    INVOKEVIRTUAL java/io/PrintStream.println (Ljava/lang/String;)V
   L9
    LINENUMBER 19 L9
    GETSTATIC java/lang/System.out : Ljava/io/PrintStream;
    ILOAD 6
    INVOKEDYNAMIC makeConcatWithConstants(I)Ljava/lang/String; [
      // handle kind 0x6 : INVOKESTATIC
      java/lang/invoke/StringConcatFactory.makeConcatWithConstants(Ljava/lang/invoke/MethodHandles$Lookup;Ljava/lang/String;Ljava/lang/invoke/MethodType;Ljava/lang/String;[Ljava/lang/Object;)Ljava/lang/invoke/CallSite;
      // arguments:
      "Duration: \u0001"
    ]
    INVOKEVIRTUAL java/io/PrintStream.println (Ljava/lang/String;)V
   L10
    LINENUMBER 21 L10
    DLOAD 2
    DLOAD 4
    ILOAD 6
    INVOKESTATIC DebtCollect/DebtPaybackCal.calculateMonthlyRate (DDI)D
    DSTORE 7
   L11
    LINENUMBER 22 L11
    DLOAD 2
    DLOAD 4
    ILOAD 6
    INVOKESTATIC DebtCollect/DebtPaybackCal.calculateOverallDebt (DDI)D
    DSTORE 9
   L12
    LINENUMBER 25 L12
    GETSTATIC java/lang/System.out : Ljava/io/PrintStream;
    LDC "\nLoan Details:"
    INVOKEVIRTUAL java/io/PrintStream.println (Ljava/lang/String;)V
   L13
    LINENUMBER 26 L13
    GETSTATIC java/lang/System.out : Ljava/io/PrintStream;
    DLOAD 7
    INVOKEDYNAMIC makeConcatWithConstants(D)Ljava/lang/String; [
      // handle kind 0x6 : INVOKESTATIC
      java/lang/invoke/StringConcatFactory.makeConcatWithConstants(Ljava/lang/invoke/MethodHandles$Lookup;Ljava/lang/String;Ljava/lang/invoke/MethodType;Ljava/lang/String;[Ljava/lang/Object;)Ljava/lang/invoke/CallSite;
      // arguments:
      "Monthly Rate: \u0001 euros"
    ]
    INVOKEVIRTUAL java/io/PrintStream.println (Ljava/lang/String;)V
   L14
    LINENUMBER 27 L14
    GETSTATIC java/lang/System.out : Ljava/io/PrintStream;
    ILOAD 6
    INVOKEDYNAMIC makeConcatWithConstants(I)Ljava/lang/String; [
      // handle kind 0x6 : INVOKESTATIC
      java/lang/invoke/StringConcatFactory.makeConcatWithConstants(Ljava/lang/invoke/MethodHandles$Lookup;Ljava/lang/String;Ljava/lang/invoke/MethodType;Ljava/lang/String;[Ljava/lang/Object;)Ljava/lang/invoke/CallSite;
      // arguments:
      "Number of Rates: \u0001"
    ]
    INVOKEVIRTUAL java/io/PrintStream.println (Ljava/lang/String;)V
   L15
    LINENUMBER 28 L15
    GETSTATIC java/lang/System.out : Ljava/io/PrintStream;
    DLOAD 9
    INVOKEDYNAMIC makeConcatWithConstants(D)Ljava/lang/String; [
      // handle kind 0x6 : INVOKESTATIC
      java/lang/invoke/StringConcatFactory.makeConcatWithConstants(Ljava/lang/invoke/MethodHandles$Lookup;Ljava/lang/String;Ljava/lang/invoke/MethodType;Ljava/lang/String;[Ljava/lang/Object;)Ljava/lang/invoke/CallSite;
      // arguments:
      "Overall Debt: \u0001 euros"
    ]
    INVOKEVIRTUAL java/io/PrintStream.println (Ljava/lang/String;)V
   L16
    LINENUMBER 30 L16
    RETURN
   L17
    LOCALVARIABLE args [Ljava/lang/String; L0 L17 0
    LOCALVARIABLE sc Ljava/util/Scanner; L1 L17 1
    LOCALVARIABLE db D L3 L17 2
    LOCALVARIABLE intrst D L5 L17 4
    LOCALVARIABLE dbdur I L7 L17 6
    LOCALVARIABLE monthlyRate D L11 L17 7
    LOCALVARIABLE overallDebt D L12 L17 9
    MAXSTACK = 5
    MAXLOCALS = 11

  // access flags 0x9
  public static calculateMonthlyintrst(D)D
   L0
    LINENUMBER 32 L0
    DLOAD 0
    LDC 12.0
    DDIV
    LDC 100.0
    DDIV
    DRETURN
   L1
    LOCALVARIABLE intrst D L0 L1 0
    MAXSTACK = 4
    MAXLOCALS = 2

  // access flags 0x9
  public static calculateMonthlyRate(DDI)D
   L0
    LINENUMBER 37 L0
    GETSTATIC java/lang/System.out : Ljava/io/PrintStream;
    DLOAD 0
    DLOAD 2
    ILOAD 4
    INVOKEDYNAMIC makeConcatWithConstants(DDI)Ljava/lang/String; [
      // handle kind 0x6 : INVOKESTATIC
      java/lang/invoke/StringConcatFactory.makeConcatWithConstants(Ljava/lang/invoke/MethodHandles$Lookup;Ljava/lang/String;Ljava/lang/invoke/MethodType;Ljava/lang/String;[Ljava/lang/Object;)Ljava/lang/invoke/CallSite;
      // arguments:
      "\nLoan Details:\u0001\u0001\u0001"
    ]
    INVOKEVIRTUAL java/io/PrintStream.println (Ljava/lang/String;)V
   L1
    LINENUMBER 38 L1
    DLOAD 2
    INVOKESTATIC DebtCollect/DebtPaybackCal.calculateMonthlyintrst (D)D
    DSTORE 5
   L2
    LINENUMBER 39 L2
    DLOAD 0
    ILOAD 4
    I2D
    DDIV
    DLOAD 5
    DADD
    DRETURN
   L3
    LOCALVARIABLE db D L0 L3 0
    LOCALVARIABLE intrst D L0 L3 2
    LOCALVARIABLE dbdur I L0 L3 4
    LOCALVARIABLE monthlyintrst D L2 L3 5
    MAXSTACK = 6
    MAXLOCALS = 7

  // access flags 0x9
  public static calculateOverallDebt(DDI)D
   L0
    LINENUMBER 44 L0
    DLOAD 0
    DLOAD 2
    ILOAD 4
    INVOKESTATIC DebtCollect/DebtPaybackCal.calculateMonthlyRate (DDI)D
    DSTORE 5
   L1
    LINENUMBER 45 L1
    DLOAD 5
    ILOAD 4
    I2D
    DMUL
    DRETURN
   L2
    LOCALVARIABLE db D L0 L2 0
    LOCALVARIABLE intrst D L0 L2 2
    LOCALVARIABLE numberOfRates I L0 L2 4
    LOCALVARIABLE monthly D L1 L2 5
    MAXSTACK = 5
    MAXLOCALS = 7
}

